igraphx_simulations/__init__.py
igraphx_simulations/modularity.py
igraphx_simulations/simulations.py
network_extensions/__init__.py
network_extensions/extendedGraph/ExtendedGraph.py
network_extensions/extendedGraph/ExtendedGraphTool.py
network_extensions/extendedGraph/ExtendedGraphToolGraph.py
network_extensions/extendedGraph/HBaseDataTypes.py
network_extensions/extendedGraph/RedisDataTypes.py
network_extensions/extendedGraph/__init__.py
network_extensions/extendedGraph/igraph_redis.py
network_extensions/helpers/__init__.py
network_extensions/helpers/convertGraphs.py
network_extensions/helpers/disambiguate.py
network_extensions/helpers/infomapHelpers.py
network_extensions/igraphx/__init__.py
network_extensions/igraphx/graph_plotly.py
network_extensions/igraphx/igraphx_cytoscape.py
network_extensions/igraphx/igraphx_gephi.py
network_extensions/igraphx/multilayer.py
network_extensions/igraphx/semantic/__init__.py
network_extensions/igraphx/semantic/corpus.py
network_extensions/igraphx/semantic/semantic.py
network_extensions-0.9.8.0.dist-info/LICENSE
network_extensions-0.9.8.0.dist-info/METADATA
network_extensions-0.9.8.0.dist-info/WHEEL
network_extensions-0.9.8.0.dist-info/top_level.txt
network_extensions-0.9.8.0.dist-info/RECORD
