Metadata-Version: 2.1
Name: network-extensions
Version: 0.9.8.0
Summary: Managing multilayer graphs with igraph
Home-page: UNKNOWN
Author: dwinter
Author-email: dwinter@mpiwg-berlin.mpg.de
License: UNKNOWN
Platform: UNKNOWN
Requires-Dist: rdflib
Requires-Dist: python-igraph
Requires-Dist: matplotlib
Requires-Dist: tqdm
Requires-Dist: pandas
Requires-Dist: plotly
Requires-Dist: colorlover
